MANIFEST.in
README.txt
setup.py
Products/__init__.py
Products.EasyAsPiIE.egg-info/PKG-INFO
Products.EasyAsPiIE.egg-info/SOURCES.txt
Products.EasyAsPiIE.egg-info/dependency_links.txt
Products.EasyAsPiIE.egg-info/entry_points.txt
Products.EasyAsPiIE.egg-info/namespace_packages.txt
Products.EasyAsPiIE.egg-info/not-zip-safe
Products.EasyAsPiIE.egg-info/requires.txt
Products.EasyAsPiIE.egg-info/top_level.txt
Products/EasyAsPiIE/__init__.py
Products/EasyAsPiIE/configure.zcml
Products/EasyAsPiIE/profiles.zcml
Products/EasyAsPiIE/setuphandlers.py
Products/EasyAsPiIE/skins.zcml
Products/EasyAsPiIE/tests.py
Products/EasyAsPiIE/Extensions/Install.py
Products/EasyAsPiIE/browser/__init__.py
Products/EasyAsPiIE/browser/configure.zcml
Products/EasyAsPiIE/browser/interfaces.py
Products/EasyAsPiIE/browser/viewlet.pt
Products/EasyAsPiIE/browser/viewlets.py
Products/EasyAsPiIE/profiles/default/Products.EasyAsPiIE_various.txt
Products/EasyAsPiIE/profiles/default/import_steps.xml
Products/EasyAsPiIE/profiles/default/jsregistry.xml
Products/EasyAsPiIE/profiles/default/metadata.xml
Products/EasyAsPiIE/profiles/default/skins.xml
Products/EasyAsPiIE/profiles/uninstall/skins.xml
Products/EasyAsPiIE/skins/EasyAsPiIE/CONTENT.txt
Products/EasyAsPiIE/skins/EasyAsPiIE/PIE.htc.dtml
Products/EasyAsPiIE/skins/EasyAsPiIE/PIE_uncompressed.htc.dtml
Products/EasyAsPiIE/skins/EasyAsPiIE/blank.gif
Products/EasyAsPiIE/skins/EasyAsPiIE/iepngfix.htc.dtml
Products/EasyAsPiIE/skins/EasyAsPiIE/selectivizr-min.js
docs/HISTORY.txt
docs/INSTALL.txt
docs/LICENSE.GPL
docs/LICENSE.txt