Metadata-Version: 1.0
Name: Products.EasyAsPiIE
Version: 3.0.1
Summary: This enables you to do CSS 3 and psuedo classes for Internet Explorer 6-8.
Home-page: https://weblion.psu.edu/svn/weblion/weblion/Products.EasyAsPiIE
Author: WebLion
Author-email: support@weblion.psu.edu
License: GPL
Keywords: web zope plone theme
Platform: UNKNOWN
Classifier: Framework :: Plone
Classifier: Programming Language :: Python
Classifier: Topic :: Software Development :: Libraries :: Python Modules
